[
  {
    "product_symbol": "C-ETH-2400-270326",
    "margin_mode": "portfolio",
    "side": "buy",
    "state": "open",
    "mmp": "disabled",
    "unfilled_size": 50,
    "bracket_stop_loss_limit_price": null,
    "id": 1107232654,
    "bracket_order": null,
    "stop_trigger_method": null,
    "average_fill_price": null,
    "quote_size": null,
    "stop_order_type": null,
    "commission": "0",
    "bracket_take_profit_limit_price": null,
    "time_in_force": "gtc",
    "bracket_stop_loss_price": null,
    "client_order_id": null,
    "trail_amount": null,
    "stop_price": null,
    "paid_commission": "0",
    "created_at": "2026-01-02T14:57:03.965735Z",
    "updated_at": "2026-01-06T08:00:36.627068Z",
    "bracket_trail_amount": null,
    "order_type": "limit_order",
    "size": 50,
    "reduce_only": false,
    "cancellation_reason": null,
    "product": {
      "contract_type": "call_options",
      "contract_unit_currency": "ETH",
      "contract_value": "0.01",
      "id": 114843,
      "notional_type": "vanilla",
      "quoting_asset": {
        "minimum_precision": 2,
        "precision": 8,
        "symbol": "USD"
      },
      "settling_asset": {
        "minimum_precision": 2,
        "precision": 8,
        "symbol": "USD"
      },
      "spot_index": {
        "symbol": ".DEETHUSD"
      },
      "symbol": "C-ETH-2400-270326",
      "tick_size": "0.01",
      "underlying_asset": {
        "minimum_precision": 4,
        "precision": 18,
        "symbol": "ETH"
      }
    },
    "bracket_take_profit_price": null,
    "limit_price": "919.01",
    "user_id": 37780748,
    "product_id": 114843,
    "meta_data": {
      "ip": "2404:7c00:4a:294c:3c2e:5651:728a:4e82",
      "otc": false,
      "source": "mobile_app_android",
      "user_updated_at": "2026-01-06T08:00:36.626Z"
    }
  },
  {
    "product_symbol": "C-ETH-2300-270226",
    "margin_mode": "portfolio",
    "side": "buy",
    "state": "open",
    "mmp": "disabled",
    "unfilled_size": 40,
    "bracket_stop_loss_limit_price": null,
    "id": 1103442700,
    "bracket_order": null,
    "stop_trigger_method": null,
    "average_fill_price": "893.01",
    "quote_size": null,
    "stop_order_type": null,
    "commission": "0",
    "bracket_take_profit_limit_price": null,
    "time_in_force": "gtc",
    "bracket_stop_loss_price": null,
    "client_order_id": null,
    "trail_amount": null,
    "stop_price": null,
    "paid_commission": "0.03706593",
    "created_at": "2025-12-30T08:23:30.131470Z",
    "updated_at": "2026-01-06T08:00:52.515873Z",
    "bracket_trail_amount": null,
    "order_type": "limit_order",
    "size": 50,
    "reduce_only": false,
    "cancellation_reason": null,
    "product": {
      "contract_type": "call_options",
      "contract_unit_currency": "ETH",
      "contract_value": "0.01",
      "id": 114371,
      "notional_type": "vanilla",
      "quoting_asset": {
        "minimum_precision": 2,
        "precision": 8,
        "symbol": "USD"
      },
      "settling_asset": {
        "minimum_precision": 2,
        "precision": 8,
        "symbol": "USD"
      },
      "spot_index": {
        "symbol": ".DEETHUSD"
      },
      "symbol": "C-ETH-2300-270226",
      "tick_size": "0.01",
      "underlying_asset": {
        "minimum_precision": 4,
        "precision": 18,
        "symbol": "ETH"
      }
    },
    "bracket_take_profit_price": null,
    "limit_price": "964.21",
    "user_id": 37780748,
    "product_id": 114371,
    "meta_data": {
      "cashflow": "-89.301",
      "ip": "110.44.115.170",
      "otc": false,
      "pnl": "-0",
      "source": "mobile_app_android",
      "user_updated_at": "2026-01-06T08:00:52.514Z"
    }
  }
]