[
  {
    "product_symbol": "P-ETH-5300-261225",
    "user_id": 37780748,
    "mmp": "disabled",
    "cancellation_reason": null,
    "bracket_take_profit_price": null,
    "paid_commission": "0",
    "time_in_force": "gtc",
    "updated_at": "2025-11-22T20:04:15.078763Z",
    "state": "open",
    "reduce_only": false,
    "id": 1047344847,
    "average_fill_price": null,
    "meta_data": {
      "ip": "2404:7c00:4a:d0ca:d2e5:e889:d821:f5db",
      "otc": false,
      "source": "mobile_app_android",
      "user_updated_at": "2025-11-22T20:04:15.078Z"
    },
    "commission": "0",
    "bracket_trail_amount": null,
    "side": "sell",
    "client_order_id": null,
    "order_type": "limit_order",
    "limit_price": 2561.59,
    "bracket_order": null,
    "trail_amount": null,
    "product": {
      "contract_type": "put_options",
      "contract_unit_currency": "ETH",
      "contract_value": "0.01",
      "id": 103987,
      "notional_type": "vanilla",
      "quoting_asset": {
        "minimum_precision": 2,
        "precision": 8,
        "symbol": "USD"
      },
      "settling_asset": {
        "minimum_precision": 2,
        "precision": 8,
        "symbol": "USD"
      },
      "spot_index": {
        "symbol": ".DEETHUSD"
      },
      "symbol": "P-ETH-5300-261225",
      "tick_size": "0.01",
      "underlying_asset": {
        "minimum_precision": 4,
        "precision": 18,
        "symbol": "ETH"
      }
    },
    "unfilled_size": 200,
    "product_id": 103987,
    "stop_price": null,
    "bracket_take_profit_limit_price": null,
    "size": 200,
    "quote_size": null,
    "stop_trigger_method": null,
    "bracket_stop_loss_limit_price": null,
    "created_at": "2025-11-20T17:20:42.125032Z",
    "bracket_stop_loss_price": null,
    "stop_order_type": null
  },
  {
    "product_symbol": "P-ETH-4500-261225",
    "user_id": 37780748,
    "mmp": "disabled",
    "cancellation_reason": null,
    "bracket_take_profit_price": null,
    "paid_commission": "0.10770507",
    "time_in_force": "gtc",
    "updated_at": "2025-11-22T20:04:19.393375Z",
    "state": "open",
    "reduce_only": false,
    "id": 1040069051,
    "average_fill_price": "1691.509166666666666667",
    "meta_data": {
      "cashflow": "405.9622",
      "ip": "2404:7c00:4a:b740:c2f9:b82:adf1:94a",
      "otc": false,
      "pnl": "-0",
      "source": "mobile_app_android",
      "user_updated_at": "2025-11-22T20:04:19.392Z"
    },
    "commission": "0",
    "bracket_trail_amount": null,
    "side": "sell",
    "client_order_id": null,
    "order_type": "limit_order",
    "limit_price": 1760.39,
    "bracket_order": null,
    "trail_amount": null,
    "product": {
      "contract_type": "put_options",
      "contract_unit_currency": "ETH",
      "contract_value": "0.01",
      "id": 103961,
      "notional_type": "vanilla",
      "quoting_asset": {
        "minimum_precision": 2,
        "precision": 8,
        "symbol": "USD"
      },
      "settling_asset": {
        "minimum_precision": 2,
        "precision": 8,
        "symbol": "USD"
      },
      "spot_index": {
        "symbol": ".DEETHUSD"
      },
      "symbol": "P-ETH-4500-261225",
      "tick_size": "0.01",
      "underlying_asset": {
        "minimum_precision": 4,
        "precision": 18,
        "symbol": "ETH"
      }
    },
    "unfilled_size": 276,
    "product_id": 103961,
    "stop_price": null,
    "bracket_take_profit_limit_price": null,
    "size": 300,
    "quote_size": null,
    "stop_trigger_method": null,
    "bracket_stop_loss_limit_price": null,
    "created_at": "2025-11-16T19:19:45.343998Z",
    "bracket_stop_loss_price": null,
    "stop_order_type": null
  },
  {
    "product_symbol": "P-ETH-4800-261225",
    "user_id": 37780748,
    "mmp": "disabled",
    "cancellation_reason": null,
    "bracket_take_profit_price": null,
    "paid_commission": "0",
    "time_in_force": "gtc",
    "updated_at": "2025-11-22T20:04:39.865960Z",
    "state": "open",
    "reduce_only": false,
    "id": 1040041117,
    "average_fill_price": null,
    "meta_data": {
      "ip": "2404:7c00:4a:b740:c2f9:b82:adf1:94a",
      "otc": false,
      "source": "mobile_app_android",
      "user_updated_at": "2025-11-22T20:04:39.865Z"
    },
    "commission": "0",
    "bracket_trail_amount": null,
    "side": "sell",
    "client_order_id": null,
    "order_type": "limit_order",
    "limit_price": "2059.89",
    "bracket_order": null,
    "trail_amount": null,
    "product": {
      "contract_type": "put_options",
      "contract_unit_currency": "ETH",
      "contract_value": "0.01",
      "id": 103978,
      "notional_type": "vanilla",
      "quoting_asset": {
        "minimum_precision": 2,
        "precision": 8,
        "symbol": "USD"
      },
      "settling_asset": {
        "minimum_precision": 2,
        "precision": 8,
        "symbol": "USD"
      },
      "spot_index": {
        "symbol": ".DEETHUSD"
      },
      "symbol": "P-ETH-4800-261225",
      "tick_size": "0.01",
      "underlying_asset": {
        "minimum_precision": 4,
        "precision": 18,
        "symbol": "ETH"
      }
    },
    "unfilled_size": 100,
    "product_id": 103978,
    "stop_price": null,
    "bracket_take_profit_limit_price": null,
    "size": 100,
    "quote_size": null,
    "stop_trigger_method": null,
    "bracket_stop_loss_limit_price": null,
    "created_at": "2025-11-16T18:53:56.306545Z",
    "bracket_stop_loss_price": null,
    "stop_order_type": null
  }
]