[
  {
    "stop_order_type": null,
    "side": "sell",
    "product_symbol": "C-ETH-2400-300126",
    "order_type": "limit_order",
    "state": "open",
    "meta_data": {
      "ip": "2404:7c00:4a:ec85:2be1:9957:9fd:98eb",
      "otc": false,
      "source": "mobile_app_android",
      "user_updated_at": "2026-01-26T07:16:31.715Z"
    },
    "product": {
      "contract_type": "call_options",
      "contract_unit_currency": "ETH",
      "contract_value": "0.01",
      "id": 107737,
      "notional_type": "vanilla",
      "quoting_asset": {
        "minimum_precision": 2,
        "precision": 8,
        "symbol": "USD"
      },
      "settling_asset": {
        "minimum_precision": 2,
        "precision": 8,
        "symbol": "USD"
      },
      "spot_index": {
        "symbol": ".DEETHUSD"
      },
      "symbol": "C-ETH-2400-300126",
      "tick_size": "0.01",
      "underlying_asset": {
        "minimum_precision": 4,
        "precision": 18,
        "symbol": "ETH"
      }
    },
    "id": 1139563365,
    "bracket_stop_loss_limit_price": null,
    "reduce_only": false,
    "limit_price": 503.19,
    "product_id": 107737,
    "time_in_force": "gtc",
    "quote_size": null,
    "created_at": "2026-01-26T07:07:15.950752Z",
    "stop_price": null,
    "average_fill_price": null,
    "user_id": 37780748,
    "commission": "0",
    "updated_at": "2026-01-26T07:16:31.715807Z",
    "bracket_take_profit_limit_price": null,
    "bracket_take_profit_price": null,
    "bracket_trail_amount": null,
    "client_order_id": null,
    "cancellation_reason": null,
    "mmp": "disabled",
    "size": 74,
    "stop_trigger_method": null,
    "trail_amount": null,
    "unfilled_size": 74,
    "bracket_stop_loss_price": null,
    "paid_commission": "0",
    "margin_mode": "portfolio",
    "bracket_order": null
  },
  {
    "stop_order_type": null,
    "side": "sell",
    "product_symbol": "C-ETH-2200-300126",
    "order_type": "limit_order",
    "state": "open",
    "meta_data": {
      "ip": "2404:7c00:4a:ec85:2be1:9957:9fd:98eb",
      "otc": false,
      "source": "mobile_app_android"
    },
    "product": {
      "contract_type": "call_options",
      "contract_unit_currency": "ETH",
      "contract_value": "0.01",
      "id": 110248,
      "notional_type": "vanilla",
      "quoting_asset": {
        "minimum_precision": 2,
        "precision": 8,
        "symbol": "USD"
      },
      "settling_asset": {
        "minimum_precision": 2,
        "precision": 8,
        "symbol": "USD"
      },
      "spot_index": {
        "symbol": ".DEETHUSD"
      },
      "symbol": "C-ETH-2200-300126",
      "tick_size": "0.01",
      "underlying_asset": {
        "minimum_precision": 4,
        "precision": 18,
        "symbol": "ETH"
      }
    },
    "id": 1139562770,
    "bracket_stop_loss_limit_price": null,
    "reduce_only": false,
    "limit_price": "1200",
    "product_id": 110248,
    "time_in_force": "gtc",
    "quote_size": null,
    "created_at": "2026-01-26T07:06:40.085453Z",
    "stop_price": null,
    "average_fill_price": null,
    "user_id": 37780748,
    "commission": "0",
    "updated_at": "2026-01-26T07:06:40.085453Z",
    "bracket_take_profit_limit_price": null,
    "bracket_take_profit_price": null,
    "bracket_trail_amount": null,
    "client_order_id": null,
    "cancellation_reason": null,
    "mmp": "disabled",
    "size": 124,
    "stop_trigger_method": null,
    "trail_amount": null,
    "unfilled_size": 124,
    "bracket_stop_loss_price": null,
    "paid_commission": "0",
    "margin_mode": "portfolio",
    "bracket_order": null
  }
]